ipython_kernel_executor.py
ipython_kernel_executor-0.1.1.dist-info/licenses/LICENSE
ipython_kernel_executor-0.1.1.dist-info/METADATA
ipython_kernel_executor-0.1.1.dist-info/WHEEL
ipython_kernel_executor-0.1.1.dist-info/top_level.txt
ipython_kernel_executor-0.1.1.dist-info/RECORD
