Metadata-Version: 2.4
Name: ipython-kernel-executor
Version: 0.1.1
Summary: A lightweight Python package to execute code in an isolated IPython kernel and capture results, stdout, and stderr.
Author-email: Jifeng Wu <jifengwu2k@gmail.com>
License-Expression: MIT
Project-URL: Homepage, https://github.com/jifengwu2k/ipython-kernel-executor
Project-URL: Bug Tracker, https://github.com/jifengwu2k/ipython-kernel-executor/issues
Classifier: Programming Language :: Python :: 2
Classifier: Programming Language :: Python :: 3
Classifier: Operating System :: OS Independent
Requires-Python: >=2
License-File: LICENSE
Requires-Dist: jupyter-client
Requires-Dist: ipykernel
Dynamic: license-file
